minmlst/__init__.py
minmlst/clustering.py
minmlst/config.py
minmlst/gene_importance.py
minmlst/input_validation.py
minmlst/tools.py
minmlst/utils.py
minmlst-0.3.4.dist-info/LICENSE
minmlst-0.3.4.dist-info/METADATA
minmlst-0.3.4.dist-info/WHEEL
minmlst-0.3.4.dist-info/top_level.txt
minmlst-0.3.4.dist-info/RECORD
