Metadata-Version: 2.1
Name: minmlst
Version: 0.3.4
Summary: Machine-learning based minimal MLST scheme for bacterial strain typing
Home-page: https://github.com/shanicohen33/minMLST
Author: Shani Cohen
Author-email: shani.cohen.33@gmail.com
License: UNKNOWN
Platform: UNKNOWN
Classifier: Programming Language :: Python :: 3
Classifier: Programming Language :: Python :: 3.6
Classifier: License :: OSI Approved :: MIT License
Classifier: Operating System :: Microsoft :: Windows
Classifier: Operating System :: POSIX :: Linux
Requires-Dist: shap (>=0.28.5)
Requires-Dist: xgboost (>=0.82)
Requires-Dist: dill (>=0.3.0)
Requires-Dist: matplotlib (>=3.0.3)
Requires-Dist: IPython (>=6.1.0)
Requires-Dist: joblib (>=0.13.2)
Requires-Dist: scikit-learn (==0.20.1)
